endless_sky/__init__.py
endless_sky/datafile.py
endless_sky/datanode.py
endless_sky_parse-0.1.2.dist-info/LICENSE
endless_sky_parse-0.1.2.dist-info/METADATA
endless_sky_parse-0.1.2.dist-info/WHEEL
endless_sky_parse-0.1.2.dist-info/top_level.txt
endless_sky_parse-0.1.2.dist-info/RECORD
