Metadata-Version: 2.1
Name: endless-sky-parse
Version: 0.1.2
Summary: A working, tested Python conversion of the C++ parser for Endless Sky DataFiles
Home-page: https://gitlab.com/spaceschluffi/endless-sky-parse
Author: SpaceSchluffi
Author-email: tr-gitlab-spaceschluffi@digital-trauma.de
License: UNKNOWN
Platform: UNKNOWN
Classifier: Programming Language :: Python :: 3
Classifier: License :: OSI Approved :: MIT License
Classifier: Operating System :: OS Independent
Requires-Python: >=3.7
Provides-Extra: test
Requires-Dist: pytest ; extra == 'test'
Requires-Dist: pytest-cov ; extra == 'test'
Requires-Dist: flake9 ; extra == 'test'
